kfg/__init__.py
kfg/config.py
kfg/version.py
kfg/yaml.py
kfg-2.0.0.dist-info/LICENSE
kfg-2.0.0.dist-info/METADATA
kfg-2.0.0.dist-info/WHEEL
kfg-2.0.0.dist-info/top_level.txt
kfg-2.0.0.dist-info/RECORD
