Metadata-Version: 2.1
Name: kfg
Version: 2.0.0
Summary: A configuration library for Python
Home-page: http://github.com/abingham/kfg
Author: Austin Bingham
Author-email: austin@sixty-north.com
License: MIT
Platform: any
Classifier: Development Status :: 3 - Alpha
Classifier: Operating System :: OS Independent
Classifier: Programming Language :: Python
Classifier: Programming Language :: Python :: 3 :: Only
Requires-Dist: pyyaml
Provides-Extra: test
Requires-Dist: hypothesis ; extra == 'test'
Requires-Dist: pytest ; extra == 'test'
Requires-Dist: tox ; extra == 'test'
